xyz_exam/__init__.py
xyz_exam/admin.py
xyz_exam/apis.py
xyz_exam/apps.py
xyz_exam/choices.py
xyz_exam/helper.py
xyz_exam/models.py
xyz_exam/receivers.py
xyz_exam/serializers.py
xyz_exam/shell.py
xyz_exam/stats.py
xyz_exam/stores.py
xyz_exam/migrations/0001_initial.py
xyz_exam/migrations/0002_auto_20200615_2112.py
xyz_exam/migrations/0003_auto_20200626_0511.py
xyz_exam/migrations/0004_auto_20200802_0028.py
xyz_exam/migrations/0005_answer_pictures.py
xyz_exam/migrations/0006_answer_grade_detail.py
xyz_exam/migrations/0007_auto_20200917_0232.py
xyz_exam/migrations/0008_exam_manual_grade.py
xyz_exam/migrations/0009_auto_20210107_0034.py
xyz_exam/migrations/0010_auto_20210331_1251.py
xyz_exam/migrations/0011_content.py
xyz_exam/migrations/0012_auto_20220917_1410.py
xyz_exam/migrations/0013_auto_20221027_1441.py
xyz_exam/migrations/0014_paper_parent_id.py
xyz_exam/migrations/0015_paper_is_editable.py
xyz_exam/migrations/0016_auto_20230411_2211.py
xyz_exam/migrations/0017_auto_20231116_0202.py
xyz_exam/migrations/0018_auto_20250421_0759.py
xyz_exam/migrations/0019_exam_user.py
xyz_exam/migrations/__init__.py
xyz_exam-0.5.0.dist-info/METADATA
xyz_exam-0.5.0.dist-info/WHEEL
xyz_exam-0.5.0.dist-info/top_level.txt
xyz_exam-0.5.0.dist-info/RECORD
